odoo/addons/sale_order_incoterm_place/README.rst
odoo/addons/sale_order_incoterm_place/__init__.py
odoo/addons/sale_order_incoterm_place/__manifest__.py
odoo/addons/sale_order_incoterm_place/i18n/ca.po
odoo/addons/sale_order_incoterm_place/i18n/es.po
odoo/addons/sale_order_incoterm_place/i18n/ja.po
odoo/addons/sale_order_incoterm_place/i18n/sale_order_incoterm_place.pot
odoo/addons/sale_order_incoterm_place/models/__init__.py
odoo/addons/sale_order_incoterm_place/models/sale_order.py
odoo/addons/sale_order_incoterm_place/readme/CONTRIBUTORS.rst
odoo/addons/sale_order_incoterm_place/readme/DESCRIPTION.rst
odoo/addons/sale_order_incoterm_place/report/sale_order_report_templates.xml
odoo/addons/sale_order_incoterm_place/static/description/icon.png
odoo/addons/sale_order_incoterm_place/static/description/index.html
odoo/addons/sale_order_incoterm_place/views/sale_order_views.xml
odoo13_addon_sale_order_incoterm_place-13.0.1.0.1.dist-info/METADATA
odoo13_addon_sale_order_incoterm_place-13.0.1.0.1.dist-info/WHEEL
odoo13_addon_sale_order_incoterm_place-13.0.1.0.1.dist-info/top_level.txt
odoo13_addon_sale_order_incoterm_place-13.0.1.0.1.dist-info/RECORD
